MANIFEST.in
README.rst
setup.cfg
setup.py
docs/HISTORY.txt
zopeskel/__init__.py
zopeskel.dexterity.egg-info/PKG-INFO
zopeskel.dexterity.egg-info/SOURCES.txt
zopeskel.dexterity.egg-info/dependency_links.txt
zopeskel.dexterity.egg-info/entry_points.txt
zopeskel.dexterity.egg-info/namespace_packages.txt
zopeskel.dexterity.egg-info/not-zip-safe
zopeskel.dexterity.egg-info/requires.txt
zopeskel.dexterity.egg-info/top_level.txt
zopeskel/dexterity/TODO.txt
zopeskel/dexterity/__init__.py
zopeskel/dexterity/dexterity.py
zopeskel/dexterity/localcommands/__init__.py
zopeskel/dexterity/localcommands/dexterity.py
zopeskel/dexterity/localcommands/templates/dexterity/behavior/+behavior_filename+.py_tmpl
zopeskel/dexterity/localcommands/templates/dexterity/behavior/configure.zcml_insert
zopeskel/dexterity/localcommands/templates/dexterity/content/+content_class_filename+.py_tmpl
zopeskel/dexterity/localcommands/templates/dexterity/content/+contenttype_classname+.txt_tmpl
zopeskel/dexterity/localcommands/templates/dexterity/content/configure.zcml_insert
zopeskel/dexterity/localcommands/templates/dexterity/content/tests.py_insert
zopeskel/dexterity/localcommands/templates/dexterity/content/+content_class_filename+_templates/sampleview.pt_tmpl
zopeskel/dexterity/localcommands/templates/dexterity/content/models/+content_class_filename+.xml
zopeskel/dexterity/localcommands/templates/dexterity/content/profiles/default/types.xml_insert
zopeskel/dexterity/localcommands/templates/dexterity/content/profiles/default/types/+types_xml_filename+.xml_tmpl
zopeskel/dexterity/templates/dexterity/bootstrap.py
zopeskel/dexterity/templates/dexterity/buildout.cfg_tmpl
zopeskel/dexterity/templates/dexterity/plone.cfg
zopeskel/dexterity/templates/dexterity/setup.cfg
zopeskel/dexterity/templates/dexterity/setup.py_tmpl
zopeskel/dexterity/templates/dexterity/+namespace_package+/+package+/INTEGRATION.txt
zopeskel/dexterity/templates/dexterity/+namespace_package+/+package+/__init__.py_tmpl
zopeskel/dexterity/templates/dexterity/+namespace_package+/+package+/configure.zcml_tmpl
zopeskel/dexterity/templates/dexterity/+namespace_package+/+package+/tests.py_tmpl
zopeskel/dexterity/templates/dexterity/+namespace_package+/+package+/locales/README.txt
zopeskel/dexterity/templates/dexterity/+namespace_package+/+package+/profiles/default/metadata.xml_tmpl
