Metadata-Version: 1.1
Name: zopeskel.dexterity
Version: 1.5.3
Summary: ZopeSkel templates for dexterity
Home-page: http://svn.plone.org/svn/collective/zopeskel.dexterity
Author: ZopeSkel Development Team
Author-email: zopeskel@lists.plone.org
License: GPL 2
Keywords: plone dexterity paster templates zopeskel
Platform: UNKNOWN
Classifier: Development Status :: 5 - Production/Stable
Classifier: Framework :: Zope3
Classifier: Framework :: Plone
Classifier: Framework :: Plone :: 4.3
Classifier: Framework :: Buildout
Classifier: Intended Audience :: Developers
Classifier: License :: OSI Approved :: GNU General Public License (GPL)
Classifier: Programming Language :: Python
Classifier: Programming Language :: Python :: 2.6
Classifier: Programming Language :: Python :: 2.7
Classifier: Topic :: Internet :: WWW/HTTP
Classifier: Topic :: Internet :: WWW/HTTP :: Dynamic Content
Classifier: Topic :: Software Development :: Code Generators
Classifier: Topic :: Software Development :: Libraries :: Python Modules
